LICENSE.txt
MANIFEST.in
README.rst
setup.cfg
setup.py
interscratch/__init__.py
interscratch/interscratchc.py
interscratch/interscratchs.py
interscratch.egg-info/PKG-INFO
interscratch.egg-info/SOURCES.txt
interscratch.egg-info/dependency_links.txt
interscratch.egg-info/entry_points.txt
interscratch.egg-info/requires.txt
interscratch.egg-info/top_level.txt
interscratch/resources/interscratch.s2e
interscratch/resources/mult_table_client.sb2
interscratch/resources/mult_table_server.sb2
interscratch/resources/test.sb2