Metadata-Version: 1.2
Name: interscratch
Version: 0.5.0
Summary: http extension to send messages between scratch projects
Home-page: https://github.com/pypa/sampleproject
Author: Vincent Guffens
Author-email: vincent.guffens@gmail.com
License: UNKNOWN
Keywords: scratch
Platform: UNKNOWN
Classifier: Development Status :: 3 - Alpha
Classifier: Intended Audience :: End Users/Desktop
Classifier: License :: OSI Approved :: GNU General Public License v3 (GPLv3)
Classifier: Programming Language :: Python :: 2.7
Requires-Python: >=2.7
